bitvector/__init__.py
bitvector/bitfield.py
bitvector/bitvector.py
bitvector/py.typed
bitvector_for_humans-0.14.4.dist-info/METADATA
bitvector_for_humans-0.14.4.dist-info/WHEEL
bitvector_for_humans-0.14.4.dist-info/licenses/LICENSE
bitvector_for_humans-0.14.4.dist-info/RECORD
