Metadata-Version: 2.4
Name: bitvector-for-humans
Version: 0.14.4
Summary: A simple pure python Bit Vector class for Humans™.
Author-email: JnyJny <erik.oshaughnessy@gmail.com>
License-File: LICENSE
Requires-Python: >=3.9
